setup.py
tx_warmongo.egg-info/PKG-INFO
tx_warmongo.egg-info/SOURCES.txt
tx_warmongo.egg-info/dependency_links.txt
tx_warmongo.egg-info/requires.txt
tx_warmongo.egg-info/top_level.txt
txwarmongo/__init__.py
txwarmongo/database.py
txwarmongo/twisted_model.py